Euler_Deconvolution/__init__.py
Euler_Deconvolution/euler.py
Euler_Deconvolution-0.1.dist-info/METADATA
Euler_Deconvolution-0.1.dist-info/WHEEL
Euler_Deconvolution-0.1.dist-info/top_level.txt
Euler_Deconvolution-0.1.dist-info/RECORD
