Metadata-Version: 2.1
Name: Euler-Deconvolution
Version: 0.1
Summary: A Python library for Euler Deconvolution in Geophysics
Home-page: https://github.com/yourusername/Euler_Deconvolution
Author: Your Name
Author-email: your.email@example.com
License: MIT
Classifier: Programming Language :: Python :: 3
Classifier: License :: OSI Approved :: MIT License
Classifier: Operating System :: OS Independent
Requires-Python: >=3.6
Requires-Dist: numpy
Requires-Dist: scipy
